prototrade/__init__.py
prototrade/__main__.py
prototrade/strategy_registry.py
prototrade/virtual_exchange.py
prototrade/exceptions/__init__.py
prototrade/exceptions/error_processor.py
prototrade/exceptions/exceptions.py
prototrade/exchange/__init__.py
prototrade/exchange/exchange.py
prototrade/file_manager/__init__.py
prototrade/file_manager/file_manager.py
prototrade/grapher/__init__.py
prototrade/grapher/grapher.py
prototrade/models/__init__.py
prototrade/models/books.py
prototrade/models/dual_heap.py
prototrade/models/enums.py
prototrade/models/error_event.py
prototrade/models/order.py
prototrade/models/quotes.py
prototrade/models/strategy.py
prototrade/models/strategy_file_locks.py
prototrade/models/subscription_event.py
prototrade/models/transaction.py
prototrade/position_management/__init__.py
prototrade/position_management/position_manager.py
prototrade/position_management/test_puller.py
prototrade/test_strategies/__init__.py
prototrade/test_strategies/test_strategy_1.py
prototrade/ticker_streamer/__init__.py
prototrade/ticker_streamer/alpaca_streamer.py
prototrade/ticker_streamer/price_updater.py
prototrade/ticker_streamer/sim_streamer.py
prototrade/ticker_streamer/subscription_manager.py
prototrade-0.0.20.dist-info/METADATA
prototrade-0.0.20.dist-info/WHEEL
prototrade-0.0.20.dist-info/top_level.txt
prototrade-0.0.20.dist-info/RECORD
