Metadata-Version: 2.1
Name: prototrade
Version: 0.0.20
Summary: UNKNOWN
Home-page: UNKNOWN
Author: Scott Parker
License: MIT
Platform: UNKNOWN
Requires-Python: >=3.8
Requires-Dist: alpaca-trade-api (==2.3.0)
Requires-Dist: dash (<3.0,>=2.5.1)
Requires-Dist: matplotlib (>=3.6.1)
Requires-Dist: numpy (>=1.23.0)
Requires-Dist: plotly (<6.0,>=5.9.0)
